[
    {
        "id": 1,
        "movie_type": "TV MiniSeries"
    },
    {
        "id": 2,
        "movie_type": "TV Series"
    },
    {
        "id": 3,
        "movie_type": "Movie"
    },
    {
        "id": 4,
        "movie_type": "Short"
    },
    {
        "id": 5,
        "movie_type": "TV Movie"
    },
    {
        "id": 6,
        "movie_type": "TV Episode"
    },
    {
        "id": 7,
        "movie_type": "TV Special"
    },
    {
        "id": 8,
        "movie_type": "Video"
    },
    {
        "id": 9,
        "movie_type": "Videogame"
    }
]